easy_pixie/__init__.py
easy_pixie/color.py
easy_pixie/shape.py
easy_pixie/text.py
easy_pixie/data/color/ui-gradient.json
easy_pixie/data/font/OPPOSans-B.ttf
easy_pixie/data/font/OPPOSans-H.ttf
easy_pixie/data/font/OPPOSans-L.ttf
easy_pixie/data/font/OPPOSans-M.ttf
easy_pixie/data/font/OPPOSans-R.ttf
easy_pixie-0.0.8.dist-info/licenses/LICENSE
easy_pixie-0.0.8.dist-info/METADATA
easy_pixie-0.0.8.dist-info/WHEEL
easy_pixie-0.0.8.dist-info/top_level.txt
easy_pixie-0.0.8.dist-info/RECORD
