Metadata-Version: 2.4
Name: Easy-Pixie
Version: 0.0.8
Summary: A tool to simplify the use of python graphic library pixie-python.
Home-page: https://github.com/Floating-Ocean
Author: Floating Ocean
Author-email: sea113290980@gmail.com
Classifier: Programming Language :: Python :: 3
Classifier: License :: OSI Approved :: MIT License
Classifier: Operating System :: OS Independent
Requires-Python: >=3.10.0
License-File: LICENSE
Requires-Dist: pixie-python>=4.3.0
Dynamic: author
Dynamic: author-email
Dynamic: classifier
Dynamic: description
Dynamic: description-content-type
Dynamic: home-page
Dynamic: license-file
Dynamic: requires-dist
Dynamic: requires-python
Dynamic: summary
